pi_robot_hat/__init__.py
pi_robot_hat/main.py
pi_robot_hat/py.typed
pi_robot_hat-0.1.0.dist-info/LICENSE
pi_robot_hat-0.1.0.dist-info/WHEEL
pi_robot_hat-0.1.0.dist-info/METADATA
pi_robot_hat-0.1.0.dist-info/RECORD
