Metadata-Version: 2.1
Name: pi-robot-hat
Version: 0.1.0
Summary: Modules for controlling the Adeept Robot Hat.
Home-page: https://github.com/cuinixam/pi-robot-hat
License: MIT
Author: cuinixam
Author-email: me@cuinixam.com
Requires-Python: >=3.9,<4.0
Classifier: Development Status :: 2 - Pre-Alpha
Classifier: Intended Audience :: Developers
Classifier: License :: OSI Approved :: MIT License
Classifier: Natural Language :: English
Classifier: Operating System :: OS Independent
Classifier: Programming Language :: Python :: 3
Classifier: Programming Language :: Python :: 3.9
Classifier: Programming Language :: Python :: 3.10
Classifier: Topic :: Software Development :: Libraries
Provides-Extra: docs
Requires-Dist: Sphinx (>=5.0,<6.0); extra == "docs"
Requires-Dist: myst-parser (>=0.18,<0.19); extra == "docs"
Requires-Dist: sphinx-rtd-theme (>=1.0,<2.0); extra == "docs"
Project-URL: Bug Tracker, https://github.com/cuinixam/pi-robot-hat/issues
Project-URL: Changelog, https://github.com/cuinixam/pi-robot-hat/blob/main/CHANGELOG.md
Project-URL: Documentation, https://pi-robot-hat.readthedocs.io
Project-URL: Repository, https://github.com/cuinixam/pi-robot-hat
